chess_heatmap_qxf2/__init__.py
chess_heatmap_qxf2/chess_control_heatmap.py
chess_heatmap_qxf2/chess_dask_cluster.py
chess_heatmap_qxf2/chess_image_generator.py
chess_heatmap_qxf2/chess_util.py
chess_heatmap_qxf2-0.0.0.23.dist-info/LICENSE
chess_heatmap_qxf2-0.0.0.23.dist-info/METADATA
chess_heatmap_qxf2-0.0.0.23.dist-info/WHEEL
chess_heatmap_qxf2-0.0.0.23.dist-info/top_level.txt
chess_heatmap_qxf2-0.0.0.23.dist-info/RECORD
